django_expanded_test_cases/__init__.py
django_expanded_test_cases/exceptions.py
django_expanded_test_cases/readme.md
django_expanded_test_cases/constants/__init__.py
django_expanded_test_cases/constants/auth_constants.py
django_expanded_test_cases/constants/debug_output_constants.py
django_expanded_test_cases/constants/general_handling_constants.py
django_expanded_test_cases/constants/selenium_constants.py
django_expanded_test_cases/mixins/__init__.py
django_expanded_test_cases/mixins/core_mixin.py
django_expanded_test_cases/mixins/live_server_mixin.py
django_expanded_test_cases/mixins/response_mixin.py
django_expanded_test_cases/templates/django_expanded_test_cases/form.html
django_expanded_test_cases/templates/django_expanded_test_cases/form_alt.html
django_expanded_test_cases/templates/django_expanded_test_cases/index.html
django_expanded_test_cases/test_cases/__init__.py
django_expanded_test_cases/test_cases/base_test_case.py
django_expanded_test_cases/test_cases/channels_live_server_test_case.py
django_expanded_test_cases/test_cases/integration_test_case.py
django_expanded_test_cases/test_cases/live_server_test_case.py
django_expanded_test_cases-0.8.1.dist-info/LICENSE
django_expanded_test_cases-0.8.1.dist-info/WHEEL
django_expanded_test_cases-0.8.1.dist-info/METADATA
django_expanded_test_cases-0.8.1.dist-info/RECORD
