Metadata-Version: 2.3
Name: django-expanded-test-cases
Version: 0.8.1
Summary: Expands the existing Django TestCase class with extra functionality.
Keywords: django,testcases,tests,unittest,unittesting
Author-email: Brandon Rodriguez <brodriguez8774@gmail.com>
Maintainer-email: Brandon Rodriguez <brodriguez8774@gmail.com>
Requires-Python: >=3.6
Classifier: Environment :: Web Environment
Classifier: Framework :: Django
Classifier: Framework :: Django :: 2
Classifier: Framework :: Django :: 2.2
Classifier: Framework :: Django :: 3
Classifier: Framework :: Django :: 3.0
Classifier: Framework :: Django :: 3.1
Classifier: Framework :: Django :: 3.2
Classifier: Framework :: Django :: 4
Classifier: Framework :: Django :: 4.0
Classifier: Framework :: Django :: 4.1
Classifier: Framework :: Django :: 4.2
Classifier: Framework :: Django :: 5.0
Classifier: Intended Audience :: Developers
Classifier: License :: OSI Approved :: MIT License
Classifier: Operating System :: OS Independent
Classifier: Programming Language :: Python
Classifier: Programming Language :: Python :: 3
Classifier: Programming Language :: Python :: 3 :: Only
Classifier: Programming Language :: Python :: 3.6
Classifier: Programming Language :: Python :: 3.7
Classifier: Programming Language :: Python :: 3.8
Classifier: Programming Language :: Python :: 3.9
Classifier: Programming Language :: Python :: 3.10
Classifier: Programming Language :: Python :: 3.11
Classifier: Programming Language :: Python :: 3.12
Classifier: Topic :: Internet :: WWW/HTTP
Classifier: Topic :: Internet :: WWW/HTTP :: Dynamic Content
Classifier: Topic :: Software Development :: Testing
Requires-Dist: django >= 2.2.0
Requires-Dist: beautifulsoup4 >= 4.11.0
Requires-Dist: black ; extra == "dev"
Requires-Dist: coverage ; extra == "dev"
Requires-Dist: pylint ; extra == "dev"
Requires-Dist: pylint-django ; extra == "dev"
Requires-Dist: doc8 ; extra == "doc"
Requires-Dist: pip-tools ; extra == "doc"
Requires-Dist: rstcheck ; extra == "doc"
Requires-Dist: sphinx ; extra == "doc"
Requires-Dist: sphinx-autobuild ; extra == "doc"
Requires-Dist: sphinx-rtd-theme ; extra == "doc"
Requires-Dist: coverage ; extra == "test"
Requires-Dist: pytest ; extra == "test"
Requires-Dist: pytest-cov ; extra == "test"
Requires-Dist: pytest-django ; extra == "test"
Requires-Dist: pytest-xdist ; extra == "test"
Project-URL: Bug Tracker, https://github.com/brodriguez8774/django-expanded-test-cases/issues
Project-URL: Documentation, https://django-expanded-test-cases.readthedocs.io/en/latest/
Project-URL: Homepage, https://github.com/brodriguez8774/django-expanded-test-cases
Project-URL: Source Code, https://github.com/brodriguez8774/django-expanded-test-cases
Provides-Extra: dev
Provides-Extra: doc
Provides-Extra: test
